tests/__init__.py
utilify/Strings.py
utilify/Variable.py
utilify/__init__.py
utilify/core.py
utilify/decorators.py
utilify-1.0.3.dist-info/METADATA
utilify-1.0.3.dist-info/WHEEL
utilify-1.0.3.dist-info/top_level.txt
utilify-1.0.3.dist-info/RECORD
