Metadata-Version: 2.4
Name: utilify
Version: 1.0.3
Summary: A lightweight utility library for various operations
Author-email: Johnathan31 <ab1049669@gmail.com>
License: MIT
Project-URL: Homepage, https://github.com/johnathan31/utilify
Requires-Python: >=3.8
